MANIFEST.in
PKG-INFO
README.txt
setup.cfg
setup.py
docs/HISTORY.txt
docs/INSTALL.txt
docs/LICENSE.GPL
docs/LICENSE.txt
medialog/.DS_Store
medialog/__init__.py
medialog.hidetitle.egg-info/PKG-INFO
medialog.hidetitle.egg-info/SOURCES.txt
medialog.hidetitle.egg-info/dependency_links.txt
medialog.hidetitle.egg-info/entry_points.txt
medialog.hidetitle.egg-info/namespace_packages.txt
medialog.hidetitle.egg-info/not-zip-safe
medialog.hidetitle.egg-info/requires.txt
medialog.hidetitle.egg-info/top_level.txt
medialog/hidetitle/.DS_Store
medialog/hidetitle/__init__.py
medialog/hidetitle/configure.zcml
medialog/hidetitle/interfaces.py
medialog/hidetitle/profiles.zcml
medialog/hidetitle/schemaextender.py
medialog/hidetitle/locales/.DS_Store
medialog/hidetitle/locales/medialog.hidetitle.pot
medialog/hidetitle/locales/plone.pot
medialog/hidetitle/locales/en/.DS_Store
medialog/hidetitle/locales/en/LC_MESSAGES/medialog.hidetitle.po
medialog/hidetitle/locales/en/LC_MESSAGES/plone.po
medialog/hidetitle/locales/no/.DS_Store
medialog/hidetitle/locales/no/LC_MESSAGES/medialog.hidetitle.po
medialog/hidetitle/locales/no/LC_MESSAGES/plone.po
medialog/hidetitle/profiles/.DS_Store
medialog/hidetitle/profiles/default/.DS_Store
medialog/hidetitle/profiles/default/browserlayer.xml
medialog/hidetitle/profiles/default/catalog.xml
medialog/hidetitle/profiles/default/metadata.xml
medialog/hidetitle/profiles/default/portal_atct.xml
medialog/hidetitle/profiles/default/skins.xml
medialog/hidetitle/profiles/default/skins/.DS_Store
medialog/hidetitle/profiles/default/skins/medialog_hidetitle/kss_generic_macros.pt
medialog/hidetitle/skins/.DS_Store
medialog/hidetitle/skins/medialog_hidetitle/kss_generic_macros.pt
medialog/hidetitle/tests/__init__.py
medialog/hidetitle/tests/base.py
medialog/hidetitle/tests/test_integration_unit.py