Metadata-Version: 1.0
Name: medialog.hidetitle
Version: 1.0
Summary: Makes it possible to mark items so the items title and description does not show.
Home-page: https://github.com/collective/medialog.hidetitle
Author: Grieg Medialog [Espen Moe-Nilssen]
Author-email: espen@medialog.no
License: GPL
Keywords: plone zope hidetitle description
Platform: UNKNOWN
Classifier: Framework :: Plone
Classifier: Programming Language :: Python
Classifier: Topic :: Software Development :: Libraries :: Python Modules
